psdoom/__init__.py
psdoom/__main__.py
psdoom/app.py
psdoom/process_manager.py
psdoom-0.1.3.dist-info/METADATA
psdoom-0.1.3.dist-info/WHEEL
psdoom-0.1.3.dist-info/entry_points.txt
psdoom-0.1.3.dist-info/RECORD
