Metadata-Version: 2.4
Name: psdoom
Version: 0.1.3
Summary: A TUI process manager inspired by the classic Doom game
License: MIT
Requires-Python: >=3.8
Requires-Dist: psutil==5.9.0
Requires-Dist: textual==0.38.1
